devdeck_home_assistant/__init__.py
devdeck_home_assistant/light_toggle_control.py
devdeck_home_assistant/switch_toggle_control.py
devdeck_home_assistant/assets/font-awesome/licence.txt
devdeck_home_assistant/assets/font-awesome/lightbulb-regular.png
devdeck_home_assistant/assets/font-awesome/lightbulb-solid.png
devdeck_home_assistant/assets/font-awesome/toggle-off-solid.png
devdeck_home_assistant/assets/font-awesome/toggle-on-solid.png
tests/__init__.py
tests/testing_utils.py
tests/devdeck_home_assistant/__init__.py
tests/devdeck_home_assistant/test_light_toggle_control.py
devdeck_home_assistant-1.0.4.dist-info/METADATA
devdeck_home_assistant-1.0.4.dist-info/WHEEL
devdeck_home_assistant-1.0.4.dist-info/top_level.txt
devdeck_home_assistant-1.0.4.dist-info/RECORD
