Metadata-Version: 2.1
Name: devdeck-home-assistant
Version: 1.0.4
Summary: Home Assistant controls for DevDeck.
Home-page: https://github.com/jamesridgway/devdeck-home-assistant
Author: James Ridgway
License: MIT
Platform: UNKNOWN
Requires-Dist: assertpy (==1.1)
Requires-Dist: devdeck-core (==1.0.7)
Requires-Dist: pytest (==6.2.1)
Requires-Dist: requests (==2.25.1)
Requires-Dist: vcrpy (==4.1.1)
